{
    "packages": [],
    "includes": {
        "include/all$e2b5e26cf31818e5e5e06cbb28a3c34627aa3bfc.json": {
            "sha1": "e2b5e26cf31818e5e5e06cbb28a3c34627aa3bfc"
        }
    },
    "metadata-url": "/satis/p2/%package%.json",
    "available-packages": [
        "advanced-custom-fields/advanced-custom-fields-pro",
        "moderntribe/composer-installer",
        "moderntribe/dev-server",
        "moderntribe/rope-plugin-core",
        "moderntribe/rope-plugin-lib",
        "moderntribe/tmc-plugin-client"
    ]
}
